MANIFEST.in
README.md
setup.py
Damian_Skier_92.egg-info/PKG-INFO
Damian_Skier_92.egg-info/SOURCES.txt
Damian_Skier_92.egg-info/dependency_links.txt
Damian_Skier_92.egg-info/requires.txt
Damian_Skier_92.egg-info/top_level.txt
bin/get_names.bat
get_names/__init__.py
get_names/get_names.py