Metadata-Version: 1.0
Name: Damian-Skier-92
Version: 0.1.1
Summary: Super useful library
Home-page: https://github.com
Author: SomeCompany PLC
Author-email: dev@example.com
License: UNKNOWN
Platform: UNKNOWN
